{
  "runtime": "nodejs16.x",
  "version": "1.0",
  "appFunctions": {
    "getCurrentUser": {
      "file": "./auth/get-current-user.js",
      "secrets": ["APP_API_KEY"]
    },
    "createUser": {
      "file": "./users/create-user.js",
      "secrets": ["APP_API_KEY"]
    },
    "getUserByHubspotUserId": {
      "file": "./users/get-user-by-hub-user-id.js",
      "secrets": ["APP_API_KEY"]
    },
    "getUpComingAppointments": {
      "file": "./appointments/get-upcoming-appointments.js",
      "secrets": ["APP_API_KEY"]
    },
    "getPastAppointments": {
      "file": "./appointments/get-past-appointments.js",
      "secrets": ["APP_API_KEY"]
    }
  }
}
